{
    "login": {
        "settings": {
            "required": {
                "templates": [
                    "demo-template"
                ]
            },
            "id": "login",
            "namespace": ""
        },
        "resource_provider": {
            "module_path": "C:\\Workspace\\Projects\\Libraries\\mad\\examples\\nodejs\\public\\modules\\login",
            "resources_path": "C:\\Workspace\\Projects\\Libraries\\mad\\examples\\nodejs\\public\\modules\\login\\resources"
        }
    },
    "login.dashboard": {
        "settings": {
            "required": {
                "templates": [
                    "demo-template"
                ]
            },
            "id": "dashboard",
            "namespace": "login"
        },
        "resource_provider": {
            "module_path": "C:\\Workspace\\Projects\\Libraries\\mad\\examples\\nodejs\\public\\modules\\login\\dashboard",
            "resources_path": "C:\\Workspace\\Projects\\Libraries\\mad\\examples\\nodejs\\public\\modules\\login\\dashboard\\resources"
        }
    }
}